survey_tools.py
survey_tools-0.1.1.dist-info/METADATA
survey_tools-0.1.1.dist-info/WHEEL
survey_tools-0.1.1.dist-info/licenses/LICENSE.txt
survey_tools-0.1.1.dist-info/RECORD
