Metadata-Version: 2.3
Name: survey_tools
Version: 0.1.1
Summary: Simple python tools for survey research analysis for users of Pandas
Project-URL: Homepage, https://github.com/acbass49/survey_tools
Project-URL: Issues, https://github.com/acbass49/survey_tools/issues
Project-URL: Vignette, https://alexbass.me/projects/survey_tools/
Author-email: Alex Bass <acbass49@gmail.com>
Maintainer-email: Alex Bass <acbass49@gmail.com>
License: Copyright (c) 2018 The Python Packaging Authority
License-File: LICENSE.txt
Keywords: Crosstabs,Recode,Survey Research,Weighting
Classifier: License :: OSI Approved :: MIT License
Classifier: Operating System :: OS Independent
Classifier: Programming Language :: Python :: 3
Requires-Python: >=3.8
Requires-Dist: pandas
Requires-Dist: pytest
